{"page": 291, "lines": [{"line": 1, "type": "text", "words": [{"location": "17:87:1", "qpcV2": "пұҒ"}, {"location": "17:87:2", "qpcV2": "пұӮ"}, {"location": "17:87:3", "qpcV2": "пұғ"}, {"location": "17:87:4", "qpcV2": "пұ„пұ…"}, {"location": "17:87:5", "qpcV2": "пұҶ"}, {"location": "17:87:6", "qpcV2": "пұҮ"}, {"location": "17:87:7", "qpcV2": "пұҲ"}, {"location": "17:87:8", "qpcV2": "пұү"}, {"location": "17:87:9", "qpcV2": "пұҠ"}, {"location": "17:87:10", "qpcV2": "пұӢ"}, {"location": "17:88:1", "qpcV2": "пұҢ"}]}, {"line": 2, "type": "text", "words": [{"location": "17:88:2", "qpcV2": "пұҚ"}, {"location": "17:88:3", "qpcV2": "пұҺ"}, {"location": "17:88:4", "qpcV2": "пұҸ"}, {"location": "17:88:5", "qpcV2": "пұҗ"}, {"location": "17:88:6", "qpcV2": "пұ‘"}, {"location": "17:88:7", "qpcV2": "пұ’"}, {"location": "17:88:8", "qpcV2": "пұ“"}, {"location": "17:88:9", "qpcV2": "пұ”"}, {"location": "17:88:10", "qpcV2": "пұ•"}, {"location": "17:88:11", "qpcV2": "пұ–"}]}, {"line": 3, "type": "text", "words": [{"location": "17:88:12", "qpcV2": "пұ—"}, {"location": "17:88:13", "qpcV2": "пұҳ"}, {"location": "17:88:14", "qpcV2": "пұҷ"}, {"location": "17:88:15", "qpcV2": "пұҡ"}, {"location": "17:88:16", "qpcV2": "пұӣ"}, {"location": "17:88:17", "qpcV2": "пұң"}, {"location": "17:88:18", "qpcV2": "пұқ"}, {"location": "17:88:19", "qpcV2": "пұһ"}, {"location": "17:88:20", "qpcV2": "пұҹ"}]}, {"line": 4, "type": "text", "words": [{"location": "17:89:1", "qpcV2": "пұ "}, {"location": "17:89:2", "qpcV2": "пұЎ"}, {"location": "17:89:3", "qpcV2": "пұў"}, {"location": "17:89:4", "qpcV2": "пұЈ"}, {"location": "17:89:5", "qpcV2": "пұӨ"}, {"location": "17:89:6", "qpcV2": "пұҘ"}, {"location": "17:89:7", "qpcV2": "пұҰ"}, {"location": "17:89:8", "qpcV2": "пұ§"}, {"location": "17:89:9", "qpcV2": "пұЁ"}, {"location": "17:89:10", "qpcV2": "пұ©"}, {"location": "17:89:11", "qpcV2": "пұӘ"}]}, {"line": 5, "type": "text", "words": [{"location": "17:89:12", "qpcV2": "пұ«"}, {"location": "17:89:13", "qpcV2": "пұ¬"}, {"location": "17:89:14", "qpcV2": "пұӯ"}, {"location": "17:89:15", "qpcV2": "пұ®"}, {"location": "17:90:1", "qpcV2": "пұҜ"}, {"location": "17:90:2", "qpcV2": "пұ°"}, {"location": "17:90:3", "qpcV2": "пұұ"}, {"location": "17:90:4", "qpcV2": "пұІ"}, {"location": "17:90:5", "qpcV2": "пұі"}, {"location": "17:90:6", "qpcV2": "пұҙ"}]}, {"line": 6, "type": "text", "words": [{"location": "17:90:7", "qpcV2": "пұө"}, {"location": "17:90:8", "qpcV2": "пұ¶"}, {"location": "17:90:9", "qpcV2": "пұ·"}, {"location": "17:90:10", "qpcV2": "пұё"}, {"location": "17:90:11", "qpcV2": "пұ№"}, {"location": "17:91:1", "qpcV2": "пұә"}, {"location": "17:91:2", "qpcV2": "пұ»"}, {"location": "17:91:3", "qpcV2": "пұј"}, {"location": "17:91:4", "qpcV2": "пұҪ"}, {"location": "17:91:5", "qpcV2": "пұҫ"}, {"location": "17:91:6", "qpcV2": "пұҝ"}]}, {"line": 7, "type": "text", "words": [{"location": "17:91:7", "qpcV2": "пІҖ"}, {"location": "17:91:8", "qpcV2": "пІҒ"}, {"location": "17:91:9", "qpcV2": "пІӮ"}, {"location": "17:91:10", "qpcV2": "пІғ"}, {"location": "17:91:11", "qpcV2": "пІ„"}, {"location": "17:91:12", "qpcV2": "пІ…"}, {"location": "17:92:1", "qpcV2": "пІҶ"}, {"location": "17:92:2", "qpcV2": "пІҮ"}, {"location": "17:92:3", "qpcV2": "пІҲ"}]}, {"line": 8, "type": "text", "words": [{"location": "17:92:4", "qpcV2": "пІү"}, {"location": "17:92:5", "qpcV2": "пІҠ"}, {"location": "17:92:6", "qpcV2": "пІӢ"}, {"location": "17:92:7", "qpcV2": "пІҢ"}, {"location": "17:92:8", "qpcV2": "пІҚ"}, {"location": "17:92:9", "qpcV2": "пІҺ"}, {"location": "17:92:10", "qpcV2": "пІҸ"}, {"location": "17:92:11", "qpcV2": "пІҗ"}]}, {"line": 9, "type": "text", "words": [{"location": "17:92:12", "qpcV2": "пІ‘"}, {"location": "17:92:13", "qpcV2": "пІ’"}, {"location": "17:93:1", "qpcV2": "пІ“"}, {"location": "17:93:2", "qpcV2": "пІ”"}, {"location": "17:93:3", "qpcV2": "пІ•"}, {"location": "17:93:4", "qpcV2": "пІ–"}, {"location": "17:93:5", "qpcV2": "пІ—"}, {"location": "17:93:6", "qpcV2": "пІҳ"}, {"location": "17:93:7", "qpcV2": "пІҷ"}, {"location": "17:93:8", "qpcV2": "пІҡ"}, {"location": "17:93:9", "qpcV2": "пІӣ"}, {"location": "17:93:10", "qpcV2": "пІң"}]}, {"line": 10, "type": "text", "words": [{"location": "17:93:11", "qpcV2": "пІқ"}, {"location": "17:93:12", "qpcV2": "пІһ"}, {"location": "17:93:13", "qpcV2": "пІҹ"}, {"location": "17:93:14", "qpcV2": "пІ "}, {"location": "17:93:15", "qpcV2": "пІЎ"}, {"location": "17:93:16", "qpcV2": "пІў"}, {"location": "17:93:17", "qpcV2": "пІЈ"}, {"location": "17:93:18", "qpcV2": "пІӨпІҘ"}, {"location": "17:93:19", "qpcV2": "пІҰ"}]}, {"line": 11, "type": "text", "words": [{"location": "17:93:20", "qpcV2": "пІ§"}, {"location": "17:93:21", "qpcV2": "пІЁ"}, {"location": "17:93:22", "qpcV2": "пІ©"}, {"location": "17:93:23", "qpcV2": "пІӘ"}, {"location": "17:93:24", "qpcV2": "пІ«"}, {"location": "17:93:25", "qpcV2": "пІ¬"}, {"location": "17:93:26", "qpcV2": "пІӯ"}, {"location": "17:93:27", "qpcV2": "пІ®"}, {"location": "17:94:1", "qpcV2": "пІҜ"}, {"location": "17:94:2", "qpcV2": "пІ°"}, {"location": "17:94:3", "qpcV2": "пІұ"}]}, {"line": 12, "type": "text", "words": [{"location": "17:94:4", "qpcV2": "пІІ"}, {"location": "17:94:5", "qpcV2": "пІі"}, {"location": "17:94:6", "qpcV2": "пІҙ"}, {"location": "17:94:7", "qpcV2": "пІө"}, {"location": "17:94:8", "qpcV2": "пІ¶"}, {"location": "17:94:9", "qpcV2": "пІ·"}, {"location": "17:94:10", "qpcV2": "пІё"}, {"location": "17:94:11", "qpcV2": "пІ№"}, {"location": "17:94:12", "qpcV2": "пІә"}, {"location": "17:94:13", "qpcV2": "пІ»"}, {"location": "17:94:14", "qpcV2": "пІј"}]}, {"line": 13, "type": "text", "words": [{"location": "17:94:15", "qpcV2": "пІҪ"}, {"location": "17:94:16", "qpcV2": "пІҫ"}, {"location": "17:95:1", "qpcV2": "пІҝ"}, {"location": "17:95:2", "qpcV2": "піҖ"}, {"location": "17:95:3", "qpcV2": "піҒ"}, {"location": "17:95:4", "qpcV2": "піӮ"}, {"location": "17:95:5", "qpcV2": "піғ"}, {"location": "17:95:6", "qpcV2": "пі„"}, {"location": "17:95:7", "qpcV2": "пі…"}, {"location": "17:95:8", "qpcV2": "піҶ"}]}, {"line": 14, "type": "text", "words": [{"location": "17:95:9", "qpcV2": "піҮ"}, {"location": "17:95:10", "qpcV2": "піҲ"}, {"location": "17:95:11", "qpcV2": "піү"}, {"location": "17:95:12", "qpcV2": "піҠ"}, {"location": "17:95:13", "qpcV2": "піӢ"}, {"location": "17:95:14", "qpcV2": "піҢ"}, {"location": "17:95:15", "qpcV2": "піҚ"}, {"location": "17:96:1", "qpcV2": "піҺ"}, {"location": "17:96:2", "qpcV2": "піҸ"}, {"location": "17:96:3", "qpcV2": "піҗ"}]}, {"line": 15, "type": "text", "words": [{"location": "17:96:4", "qpcV2": "пі‘"}, {"location": "17:96:5", "qpcV2": "пі’"}, {"location": "17:96:6", "qpcV2": "пі“пі”"}, {"location": "17:96:7", "qpcV2": "пі•"}, {"location": "17:96:8", "qpcV2": "пі–"}, {"location": "17:96:9", "qpcV2": "пі—"}, {"location": "17:96:10", "qpcV2": "піҳ"}, {"location": "17:96:11", "qpcV2": "піҷ"}, {"location": "17:96:12", "qpcV2": "піҡ"}]}]}